<annotation>
	<folder>cat</folder>
	<filename>cat30.png</filename>
	<path>C:\Users\talha\OneDrive\images\cat\cat30.png</path>
	<source>
		<database>Unknown</database>
	</source>
	<size>
		<width>275</width>
		<height>183</height>
		<depth>3</depth>
	</size>
	<segmented>0</segmented>
	<object>
		<name>cat</name>
		<pose>Unspecified</pose>
		<truncated>1</truncated>
		<difficult>0</difficult>
		<bndbox>
			<xmin>31</xmin>
			<ymin>2</ymin>
			<xmax>194</xmax>
			<ymax>183</ymax>
		</bndbox>
	</object>
</annotation>
